composabl/core.cpython-311-aarch64-linux-gnu.so
composabl/__init__.cpython-311-aarch64-linux-gnu.so
composabl/ray.cpython-311-aarch64-linux-gnu.so
composabl_dev-0.19.1.dist-info/METADATA
composabl_dev-0.19.1.dist-info/entry_points.txt
composabl_dev-0.19.1.dist-info/RECORD
composabl_dev-0.19.1.dist-info/top_level.txt
composabl_dev-0.19.1.dist-info/WHEEL
