Metadata-Version: 2.4
Name: composabl-dev
Version: 0.19.1
Summary: a distributed trainer to be able to train agents across a cluster of machines
Author-email: Hunter Park <hunter@composabl.io>
Requires-Python: >=3.10, <3.13
Requires-Dist: composabl-api-dev>=0.19.1
Requires-Dist: composabl-core-dev>=0.19.1
Requires-Dist: composabl-train-dev>=0.19.1
Requires-Dist: composabl-cli-dev>=0.19.1
Dynamic: description
Dynamic: description-content-type
Dynamic: requires-python
